pyrostest/__init__.py
pyrostest/launch_tools.py
pyrostest/ros_test.py
pyrostest/rostest_utils.py
pyrostest-0.1.13.dist-info/DESCRIPTION.rst
pyrostest-0.1.13.dist-info/METADATA
pyrostest-0.1.13.dist-info/RECORD
pyrostest-0.1.13.dist-info/WHEEL
pyrostest-0.1.13.dist-info/metadata.json
pyrostest-0.1.13.dist-info/top_level.txt
