Metadata-Version: 2.0
Name: pyrostest
Version: 0.1.13
Summary: The most lit ros testing framework
Home-page: https://github.com/gtagency/pyrostest
Author: Raphael Gontijo Lopes
Author-email: raphaelgontijolopes@gmail.com
License: MIT
Platform: UNKNOWN
Classifier: Programming Language :: Python
Classifier: Programming Language :: Python :: 2.7
Classifier: Programming Language :: Python :: 3.5
Requires-Dist: psutil (==5.1.3)
Requires-Dist: six (==1.11.0)
